README.rst
setup.py
sqlconstruct.py
SQLConstruct.egg-info/PKG-INFO
SQLConstruct.egg-info/SOURCES.txt
SQLConstruct.egg-info/dependency_links.txt
SQLConstruct.egg-info/requires.txt
SQLConstruct.egg-info/top_level.txt