Metadata-Version: 1.1
Name: SQLConstruct
Version: 0.2.1
Summary: Functional approach to query database using SQLAlchemy
Home-page: https://github.com/vmagamedov/sqlconstruct
Author: Vladimir Magamedov
Author-email: vladimir@magamedov.com
License: BSD
Platform: UNKNOWN
Classifier: Development Status :: 5 - Production/Stable
Classifier: Intended Audience :: Developers
Classifier: License :: OSI Approved :: BSD License
Classifier: Operating System :: OS Independent
Classifier: Programming Language :: Python
Classifier: Programming Language :: Python :: 3
Classifier: Programming Language :: Python :: Implementation :: CPython
Classifier: Programming Language :: Python :: Implementation :: PyPy
Classifier: Topic :: Database :: Front-Ends
